Metadata-Version: 2.4
Name: identityservice-pythonsdk
Version: 1.0.8
Summary: Python SDK for IdentityService integration with multi-tenant authentication, JWT management, and gRPC services
Author: D3 Security
Author-email: IdentityService Team <support@identityservice.com>
Maintainer-email: IdentityService Team <support@identityservice.com>
License: MIT License
Keywords: authentication,jwt,etcd,identity,security,multi-tenant
Classifier: Development Status :: 5 - Production/Stable
Classifier: Intended Audience :: Developers
Classifier: License :: OSI Approved :: MIT License
Classifier: Operating System :: OS Independent
Classifier: Programming Language :: Python :: 3
Classifier: Programming Language :: Python :: 3.8
Classifier: Programming Language :: Python :: 3.9
Classifier: Programming Language :: Python :: 3.10
Classifier: Programming Language :: Python :: 3.11
Classifier: Programming Language :: Python :: 3.12
Classifier: Topic :: Software Development :: Libraries :: Python Modules
Classifier: Topic :: Security :: Cryptography
Classifier: Topic :: System :: Distributed Computing
Requires-Python: >=3.8
License-File: LICENSE
Requires-Dist: cryptography>=41.0.0
Requires-Dist: PyJWT>=2.8.0
Requires-Dist: etcd3>=0.12.0
Requires-Dist: aiohttp>=3.9.0
Requires-Dist: pydantic>=2.5.0
Requires-Dist: dataclasses-json>=0.6.0
Requires-Dist: python-dateutil>=2.8.0
Requires-Dist: typing-extensions>=4.0.0
Requires-Dist: grpcio>=1.60.0
Requires-Dist: grpcio-tools>=1.60.0
Requires-Dist: googleapis-common-protos>=1.62.0
Provides-Extra: dev
Requires-Dist: pytest>=7.0.0; extra == "dev"
Requires-Dist: pytest-asyncio>=0.21.0; extra == "dev"
Requires-Dist: pytest-mock>=3.10.0; extra == "dev"
Requires-Dist: black>=23.0.0; extra == "dev"
Requires-Dist: isort>=5.12.0; extra == "dev"
Requires-Dist: mypy>=1.0.0; extra == "dev"
Provides-Extra: fastapi
Requires-Dist: fastapi>=0.100.0; extra == "fastapi"
Provides-Extra: redis
Requires-Dist: redis>=5.0.0; extra == "redis"
Provides-Extra: grpc
Requires-Dist: grpcio>=1.60.0; extra == "grpc"
Requires-Dist: grpcio-tools>=1.60.0; extra == "grpc"
Requires-Dist: googleapis-common-protos>=1.62.0; extra == "grpc"
Provides-Extra: all
Requires-Dist: identityservice-pythonsdk[dev,fastapi,grpc,redis]; extra == "all"
Dynamic: author
Dynamic: license-file
Dynamic: requires-python
